elasticsearch_llm_cache/elasticsearch_llm_cache.py
elasticsearch_llm_cache-0.9.5.dist-info/LICENSE
elasticsearch_llm_cache-0.9.5.dist-info/METADATA
elasticsearch_llm_cache-0.9.5.dist-info/WHEEL
elasticsearch_llm_cache-0.9.5.dist-info/top_level.txt
elasticsearch_llm_cache-0.9.5.dist-info/RECORD
